mongodb/__init__.py
feedparer-3.0.3.dist-info/LICENSE
feedparer-3.0.3.dist-info/METADATA
feedparer-3.0.3.dist-info/WHEEL
feedparer-3.0.3.dist-info/top_level.txt
feedparer-3.0.3.dist-info/RECORD
